__init__.py
SMKBO/__init__.py
SMKBO/bo.py
SMKBO/utils.py
SMKBO/cas/__init__.py
SMKBO/cas/kernels.py
SMKBO/cas/localbo_cat.py
SMKBO/cas/localbo_mixed.py
SMKBO/cas/localbo_utils.py
SMKBO/cas/optimizer.py
SMKBO/cas/optimizer_cont.py
SMKBO/cas/optimizer_mixed.py
SMKBO/spectral/__init__.py
SMKBO/spectral/adaptive_kernel.py
SMKBO/spectral/cauchy_spectral_mixture.py
SMKBO/spectral/gp_regression.py
SMKBO/spectral/sinc_kernel.py
SMKBO/test_func/__init__.py
SMKBO/test_func/base.py
SMKBO/test_func/categorical.py
SMKBO/test_func/continuous.py
SMKBO/test_func/mixed.py
smkbo-0.0.2.dist-info/METADATA
smkbo-0.0.2.dist-info/WHEEL
smkbo-0.0.2.dist-info/top_level.txt
smkbo-0.0.2.dist-info/RECORD
