Metadata-Version: 2.4
Name: SMKBO
Version: 0.0.2
Summary: Spectral mixture kernel for Bayesian Optimization
Author-email: Yi Zhang <z-yi24@mails.tsinghua.edu.cn>
License: MIT
Project-URL: Homepage, https://github.com/YyyyyyiZ/SMKBO
Classifier: Programming Language :: Python :: 3
Classifier: License :: OSI Approved :: MIT License
Classifier: Operating System :: OS Independent
Requires-Python: >=3.9
